awave/__init__.py
awave/losses.py
awave/transform.py
awave/transform1d.py
awave/transform2d.py
awave/data/__init__.py
awave/data/biology.py
awave/data/cosmology.py
awave/data/mnist.py
awave/data/resize_imgs.py
awave/data/simulation.py
awave/models/__init__.py
awave/models/models.py
awave/trim/__init__.py
awave/trim/attributions.py
awave/trim/funcs.py
awave/trim/transforms_np.py
awave/trim/transforms_torch.py
awave/trim/trim.py
awave/trim/util.py
awave/utils/__init__.py
awave/utils/evaluate.py
awave/utils/lowlevel.py
awave/utils/misc.py
awave/utils/scheduling.py
awave/utils/train.py
awave/utils/visualize.py
awave/utils/warmstart.py
awave/utils/wave_attributions.py
awave-0.1.dist-info/LICENSE
awave-0.1.dist-info/METADATA
awave-0.1.dist-info/WHEEL
awave-0.1.dist-info/top_level.txt
awave-0.1.dist-info/RECORD
