Metadata-Version: 2.1
Name: awave
Version: 0.1
Summary: Adaptive wavelets
Home-page: https://github.com/Yu-Group/adaptive-wavelet-distillation
Author: Wooseok Ha, Chandan Singh
Author-email: haywse@berkeley.edu
License: UNKNOWN
Platform: UNKNOWN
Classifier: Programming Language :: Python :: 3
Classifier: License :: OSI Approved :: MIT License
Classifier: Operating System :: OS Independent
Requires-Python: >=3.6
License-File: LICENSE
Requires-Dist: torch (>=1.0)
Requires-Dist: numpy
Requires-Dist: pywavelets
